<?xml version="1.0" encoding="UTF-8"?>
<!DOCTYPE hibernate-mapping PUBLIC "-//Hibernate/Hibernate Mapping DTD 3.0//EN" "http://www.hibernate.org/dtd/hibernate-mapping-3.0.dtd">
<!-- Generated 7/12/2013 11:46:38 AM by Hibernate Tools 3.6.0 -->
<hibernate-mapping>
  <class catalog="clinicadental" name="com.clinica.modelo.Proveedor" table="proveedores">
    <id name="id" type="java.lang.Integer">
      <column name="Id"/>
      <generator class="identity"/>
    </id>
    <property name="nombre" type="string">
      <column length="100" name="Nombre"/>
    </property>
    <property name="direccion" type="string">
      <column length="100" name="Direccion"/>
    </property>
    <property name="telefono" type="string">
      <column length="100" name="Telefono"/>
    </property>
    <property name="rfc" type="string">
      <column length="100" name="Rfc"/>
    </property>
  </class>
</hibernate-mapping>
